pywebtransport/__init__.py
pywebtransport/_adapter/__init__.py
pywebtransport/_adapter/base.py
pywebtransport/_adapter/client.py
pywebtransport/_adapter/pending.py
pywebtransport/_adapter/server.py
pywebtransport/_adapter/utils.py
pywebtransport/_protocol/__init__.py
pywebtransport/_protocol/events.py
pywebtransport/_wtransport.abi3.so
pywebtransport/_wtransport.pyi
pywebtransport/client/__init__.py
pywebtransport/client/client.py
pywebtransport/client/fleet.py
pywebtransport/client/reconnecting.py
pywebtransport/client/utils.py
pywebtransport/config.py
pywebtransport/connection.py
pywebtransport/constants.py
pywebtransport/events.py
pywebtransport/exceptions.py
pywebtransport/manager/__init__.py
pywebtransport/manager/_base.py
pywebtransport/manager/connection.py
pywebtransport/manager/session.py
pywebtransport/messaging/__init__.py
pywebtransport/messaging/datagram.py
pywebtransport/messaging/stream.py
pywebtransport/py.typed
pywebtransport/serializer/__init__.py
pywebtransport/serializer/_base.py
pywebtransport/serializer/json.py
pywebtransport/serializer/msgpack.py
pywebtransport/serializer/protobuf.py
pywebtransport/server/__init__.py
pywebtransport/server/app.py
pywebtransport/server/cluster.py
pywebtransport/server/middleware.py
pywebtransport/server/router.py
pywebtransport/server/server.py
pywebtransport/session.py
pywebtransport/stream.py
pywebtransport/types.py
pywebtransport/utils.py
pywebtransport/version.py
pywebtransport-0.12.0.dist-info/METADATA
pywebtransport-0.12.0.dist-info/WHEEL
pywebtransport-0.12.0.dist-info/licenses/LICENSE
pywebtransport-0.12.0.dist-info/licenses/NOTICE
pywebtransport-0.12.0.dist-info/RECORD
