Metadata-Version: 2.4
Name: pywebtransport
Version: 0.12.0
Classifier: Development Status :: 4 - Beta
Classifier: Framework :: AsyncIO
Classifier: Intended Audience :: Developers
Classifier: License :: OSI Approved :: Apache Software License
Classifier: Operating System :: OS Independent
Classifier: Programming Language :: Python :: 3
Classifier: Programming Language :: Python :: 3.12
Classifier: Programming Language :: Python :: 3.13
Classifier: Programming Language :: Rust
Classifier: Topic :: Communications
Classifier: Topic :: Internet
Classifier: Topic :: Internet :: WWW/HTTP
Classifier: Topic :: Software Development :: Libraries :: Python Modules
Classifier: Topic :: System :: Networking
Classifier: Typing :: Typed
Requires-Dist: aioquic>=1.3.0,<2.0.0
Requires-Dist: pywebtransport[msgpack,protobuf] ; extra == 'all'
Requires-Dist: black>=26.1.0,<27.0.0 ; extra == 'dev'
Requires-Dist: flake8>=7.3.0,<8.0.0 ; extra == 'dev'
Requires-Dist: isort>=7.0.0,<8.0.0 ; extra == 'dev'
Requires-Dist: maturin[patchelf]>=1.11.5,<2.0 ; extra == 'dev'
Requires-Dist: mypy>=1.19.1,<2.0.0 ; extra == 'dev'
Requires-Dist: pywebtransport[all,test] ; extra == 'dev'
Requires-Dist: mkdocs>=1.6.1,<2.0.0 ; extra == 'docs'
Requires-Dist: mkdocs-material>=9.7.1,<10.0.0 ; extra == 'docs'
Requires-Dist: mkdocstrings[python]>=1.0.2,<2.0.0 ; extra == 'docs'
Requires-Dist: msgpack>=1.1.2,<2.0.0 ; extra == 'msgpack'
Requires-Dist: protobuf>=6.33.5,<7.0.0 ; extra == 'protobuf'
Requires-Dist: psutil>=7.2.2,<8.0.0 ; extra == 'test'
Requires-Dist: pytest>=9.0.2,<10.0.0 ; extra == 'test'
Requires-Dist: pytest-asyncio>=1.3.0,<2.0.0 ; extra == 'test'
Requires-Dist: pytest-benchmark>=5.2.3,<6.0.0 ; extra == 'test'
Requires-Dist: pytest-cov>=7.0.0,<8.0.0 ; extra == 'test'
Requires-Dist: pytest-mock>=3.15.1,<4.0.0 ; extra == 'test'
Requires-Dist: types-psutil>=7.2.2.20260130,<8.0.0 ; extra == 'test'
Requires-Dist: uvloop>=0.22.1,<1.0.0 ; extra == 'test'
Provides-Extra: all
Provides-Extra: dev
Provides-Extra: docs
Provides-Extra: msgpack
Provides-Extra: protobuf
Provides-Extra: test
License-File: LICENSE
License-File: NOTICE
Summary: An async-native WebTransport stack for Python.
Keywords: async,http3,networking,protocol,quic,rust,webtransport
Author-email: The WTransport Authors <admin@wtransport.org>
Requires-Python: >=3.12
Project-URL: Changelog, https://github.com/wtransport/pywebtransport/blob/main/CHANGELOG.md
Project-URL: Documentation, https://python.wtransport.org
Project-URL: Homepage, https://github.com/wtransport/pywebtransport
Project-URL: Issues, https://github.com/wtransport/pywebtransport/issues
Project-URL: Repository, https://github.com/wtransport/pywebtransport.git
